{
	"geode": "4.7.0",
	"gd": {
		"win": "2.2074",
		"android": "2.2074",
		"mac": "2.2074",
		"ios": "2.2074"
	},
	"id": "ninxout.jamesmod",
	"name": "JamesMod",
	"version": "v1.0.1",
	"developer": "ninXout",
	"description": "jett james mod",
	"settings": {
		"instant-scroll": {
			"type": "bool",
			"name": "Disable Scroll Animation",
			"description": "Remove the scroll animation and instead make scrolling to the top or bottom of a list instant.",
			"default": false
		},
		"move-delete-button": {
			"type": "bool",
			"name": "Move \"Remove from Server\" button",
			"description": "Fix an issue with the favorite button and Remove from Server button overlapping.",
			"default": false
		}
	}
}
